multipart.py
multipart-1.2.0.dist-info/WHEEL
multipart-1.2.0.dist-info/METADATA
multipart-1.2.0.dist-info/RECORD
