Metadata-Version: 2.3
Name: multipart
Version: 1.2.0
Summary: Parser for multipart/form-data
Author-email: Marcel Hellkamp <marc@gsites.de>
Requires-Python: >=3.8
Classifier: Development Status :: 6 - Mature
Classifier: Intended Audience :: Developers
Classifier: License :: OSI Approved :: MIT License
Classifier: Topic :: Internet :: WWW/HTTP
Classifier: Topic :: Internet :: WWW/HTTP :: Dynamic Content
Classifier: Topic :: Internet :: WWW/HTTP :: Dynamic Content :: CGI Tools/Libraries
Classifier: Topic :: Internet :: WWW/HTTP :: WSGI
Classifier: Programming Language :: Python :: 3
Requires-Dist: pytest ; extra == "dev"
Requires-Dist: pytest-cov ; extra == "dev"
Requires-Dist: build ; extra == "dev"
Requires-Dist: twine ; extra == "dev"
Requires-Dist: sphinx>=8,<9 ; extra == "docs"
Requires-Dist: sphinx-autobuild ; extra == "docs"
Project-URL: Changelog, https://multipart.readthedocs.io/en/latest/changelog.html
Project-URL: Documentation, https://multipart.readthedocs.io/
Project-URL: Homepage, https://multipart.readthedocs.io/
Project-URL: Issues, https://github.com/defnull/multipart/issues
Project-URL: PyPI, https://pypi.org/project/multipart/
Project-URL: Source, https://github.com/defnull/multipart
Provides-Extra: dev
Provides-Extra: docs
